streamlit_monaco_editor/__init__.py
streamlit_monaco_editor/flags.py
streamlit_monaco_editor/render.py
streamlit_monaco_editor/frontend/build/404.html
streamlit_monaco_editor/frontend/build/index.html
streamlit_monaco_editor/frontend/build/_next/static/chunks/583.6eb60e0e19a36bdd.js
streamlit_monaco_editor/frontend/build/_next/static/chunks/87.feb3e53f29507729.js
streamlit_monaco_editor/frontend/build/_next/static/chunks/framework-f818b5a5e39b2c1d.js
streamlit_monaco_editor/frontend/build/_next/static/chunks/main-12e9c77dbbe57e7c.js
streamlit_monaco_editor/frontend/build/_next/static/chunks/polyfills-c67a75d1b6f99dc8.js
streamlit_monaco_editor/frontend/build/_next/static/chunks/webpack-2f0b8a3a45a83619.js
streamlit_monaco_editor/frontend/build/_next/static/chunks/pages/_app-17d19c65739e24e7.js
streamlit_monaco_editor/frontend/build/_next/static/chunks/pages/_error-8b31ab893441781f.js
streamlit_monaco_editor/frontend/build/_next/static/chunks/pages/index-bccd7a6c9389b5db.js
streamlit_monaco_editor/frontend/build/_next/static/oDOc1jC1SNGabTBICw4op/_buildManifest.js
streamlit_monaco_editor/frontend/build/_next/static/oDOc1jC1SNGabTBICw4op/_ssgManifest.js
streamlit_monaco_editor-0.1.6.dist-info/licenses/LICENSE
streamlit_monaco_editor-0.1.6.dist-info/METADATA
streamlit_monaco_editor-0.1.6.dist-info/WHEEL
streamlit_monaco_editor-0.1.6.dist-info/top_level.txt
streamlit_monaco_editor-0.1.6.dist-info/RECORD
