Metadata-Version: 2.4
Name: streamlit-monaco-editor
Version: 0.1.6
Summary: Monaco Editor (Visual Studio Code) for Streamlit
Home-page: https://vs-code.streamlit.app/
Author: marcusschiesser, KayumovRu
License: MIT
Requires-Python: >=3.9
License-File: LICENSE
Requires-Dist: streamlit>=1.20
Dynamic: license-file
